{
    "config": {
        "frequency_in_sec": 300
    },
    "urls": [
        {
            "url": "https://www.google.com",
            "timeout": 10,
            "expected_status": 200,
            "expected_text": "Google"
        },
        {
            "url": "https://httpbin.org/status/200",
            "timeout": 15,
            "expected_status": 200
        },
        {
            "url": "http://localhost:8080/health",
            "timeout": 5,
            "expected_status": 200,
            "expected_text": "OK"
        }
    ]
}